Workbook

Sheet Final (2)
A1: Unique ID | B1: title | C1: artist | D1: year | E1: decade | F1: original_vocal | G1: categories | H1: social_singing
A2: =CONCATENATE(B2,C2) -> 23Chayce Beckham | B2: 23 | C2: Chayce Beckham | D2: 2021 | E2: 2020s | F2: Male | G2: Country
A3: =CONCATENATE(B3,C3) -> 23Sam Hunt | B3: 23 | C3: Sam Hunt | D3: 2021 | E3: 2020s | F3: Male | G3: Country
A4: =CONCATENATE(B4,C4) -> 45Shinedown | B4: 45 | C4: Shinedown | D4: 2003 | E4: 2000s | F4: Male | G4: Rock
A5: =CONCATENATE(B5,C5) -> 1985Bowling for Soup | B5: 1985 | C5: Bowling for Soup | D5: 2004 | E5: 2000s | F5: Male | G5: Emo / Pop Punk | H5: Group Songs
A6: =CONCATENATE(B6,C6) -> 3005Childish Gambino | B6: 3005 | C6: Childish Gambino | D6: 2013 | E6: 2010s | F6: Male | G6: Hip-Hop
A7: =CONCATENATE(B7,C7) -> #SELFIEThe Chainsmokers | B7: #SELFIE | C7: The Chainsmokers | D7: 2014 | E7: 2010s | F7: Female | G7: EDM / Pop
A8: =CONCATENATE(B8,C8) -> (I Can't Get No) SatisfactionThe Rolling Stones | B8: (I Can't Get No) Satisfaction | C8: The Rolling Stones | D8: 1965 | E8: 1960s | F8: Male | G8: Rock | H8: Group Songs
A9: =CONCATENATE(B9,C9) -> (Kissed You) Good NightGloriana | B9: (Kissed You) Good Night | C9: Gloriana | D9: 2012 | E9: 2010s | F9: Mixed | G9: Country
A10: =CONCATENATE(B10,C10) -> (You Make Me Feel Like) A Natural WomanCarole King | B10: (You Make Me Feel Like) A Natural Woman | C10: Carole King | D10: 1971 | E10: 1970s | F10: Female | G10: Soul / Pop
A11: =CONCATENATE(B11,C11) -> 'Til Summer Comes AroundKeith Urban | B11: 'Til Summer Comes Around | C11: Keith Urban | D11: 2009 | E11: 2000s | F11: Male | G11: Country
A12: =CONCATENATE(B12,C12) -> 'Til You Can'tCody Johnson | B12: 'Til You Can't | C12: Cody Johnson | D12: 2021 | E12: 2020s | F12: Male | G12: Country
A13: =CONCATENATE(B13,C13) -> 0 to 100 / The Catch Up (Explicit)Drake | B13: 0 to 100 / The Catch Up (Explicit) | C13: Drake | D13: 2014 | E13: 2010s | F13: Male | G13: Hip-Hop, Rap
A14: =CONCATENATE(B14,C14) -> 1, 2 ManyLuke Combs ft. Brooks & Dunn | B14: 1, 2 Many | C14: Luke Combs ft. Brooks & Dunn | D14: 2019 | E14: 2010s | F14: Male | G14: Country
A15: =CONCATENATE(B15,C15) -> 1, 2, 3, 4Plain White T's | B15: 1, 2, 3, 4 | C15: Plain White T's | D15: 2008 | E15: 2000s | F15: Male | G15: Pop
A16: =CONCATENATE(B16,C16) -> 10 Million PeopleExample | B16: 10 Million People | C16: Example | D16: 2014 | E16: 2010s | F16: Male | G16: Pop
A17: =CONCATENATE(B17,C17) -> 10 Things I Hate About YouLeah Kate | B17: 10 Things I Hate About You | C17: Leah Kate | D17: 2022 | E17: 2020s | F17: Female | G17: Pop
A18: =CONCATENATE(B18,C18) -> 10,000 HoursDan + Shay & Justin Bieber | B18: 10,000 Hours | C18: Dan + Shay & Justin Bieber | D18: 2019 | E18: 2010s | F18: Male | G18: Pop/Country
A19: =CONCATENATE(B19,C19) -> 18 and LifeSkid Row | B19: 18 and Life | C19: Skid Row | D19: 1989 | E19: 1980s | F19: Male | G19: Metal / Hard Rock
A20: =CONCATENATE(B20,C20) -> 1-800-273-8255Logic ft. Alessia Cara & Khalid | B20: 1-800-273-8255 | C20: Logic ft. Alessia Cara & Khalid | D20: 2017 | E20: 2010s | F20: Mixed | G20: Hip-Hop
... A34: =CONCATENATE(B34,C34) -> 8 Second RideJake Owen | B34: 8 Second Ride | C34: Jake Owen | D34: 2006 | E34: 2000s | F34: Male | G34: Country
A35: =CONCATENATE(B35,C35) -> 90's CountryWalker Hayes | B35: 90's Country | C35: Walker Hayes | D35: 2022 | E35: 2020s | F35: Male | G35: Country | H35: Group Songs
A36: =CONCATENATE(B36,C36) -> 99 LuftballonsNena | B36: 99 Luftballons | C36: Nena | D36: 1983 | E36: 1980s | F36: Female | G36: Pop | H36: Group Songs
A37: =CONCATENATE(B37,C37) -> A Bar Song (Tipsy)Shaboozey | B37: A Bar Song (Tipsy) | C37: Shaboozey | D37: 2024 | E37: 2020s | F37: Male | G37: Country/Hip-Hop
A38: =CONCATENATE(B38,C38) -> A Billion GirlsElyar Fox | B38: A Billion Girls | C38: Elyar Fox | D38: 2014 | E38: 2010s | F38: Male | G38: Pop
A39: =CONCATENATE(B39,C39) -> A Different WorldBucky Covington | B39: A Different World | C39: Bucky Covington | D39: 2007 | E39: 2000s | F39: Male | G39: Country
A40: =CONCATENATE(B40,C40) -> A Good Hearted WomanLeAnn Rimes | B40: A Good Hearted Woman | C40: LeAnn Rimes | D40: 1999 | E40: 1990s | F40: Female | G40: Country
A41: =CONCATENATE(B41,C41) -> A Guy Walks into a BarTyler Farr | B41: A Guy Walks into a Bar | C41: Tyler Farr | D41: 2015 | E41: 2010s | F41: Male | G41: Country
A42: =CONCATENATE(B42,C42) -> A Little Bit OffFive Finger Death Punch | B42: A Little Bit Off | C42: Five Finger Death Punch | D42: 2020 | E42: 2020s | F42: Male | G42: Rock
A43: =CONCATENATE(B43,C43) -> A Little Dive Bar in DahlonegaAshley McBryde | B43: A Little Dive Bar in Dahlonega | C43: Ashley McBryde | D43: 2017 | E43: 2010s | F43: Female | G43: Country
A44: =CONCATENATE(B44,C44) -> A Little More SummertimeJason Aldean | B44: A Little More Summertime | C44: Jason Aldean | D44: 2016 | E44: 2010s | F44: Male | G44: Country
A45: =CONCATENATE(B45,C45) -> A Little More YouLittle Big Town | B45: A Little More You | C45: Little Big Town | D45: 2007 | E45: 2000s | F45: Mixed | G45: Country
A46: =CONCATENATE(B46,C46) -> A Love That Will LastRenee Olstead | B46: A Love That Will Last | C46: Renee Olstead | D46: 2004 | E46: 2000s | F46: Female | G46: Jazz / Pop
A47: =CONCATENATE(B47,C47) -> A Million DreamsThe Greatest Showman Cast | B47: A Million Dreams | C47: The Greatest Showman Cast | D47: 2017 | E47: 2010s | F47: Mixed | G47: Musical
A48: =CONCATENATE(B48,C48) -> A Quick Death in TexasClutch | B48: A Quick Death in Texas | C48: Clutch | D48: 2022 | E48: 2020s | F48: Male | G48: Rock
A49: =CONCATENATE(B49,C49) -> A Sky Full of StarsColdplay | B49: A Sky Full of Stars | C49: Coldplay | D49: 2014 | E49: 2010s | F49: Male | G49: Pop, Rock | H49: Group Songs
A50: =CONCATENATE(B50,C50) -> A Symptom of Being HumanShinedown | B50: A Symptom of Being Human | C50: Shinedown | D50: 2022 | E50: 2020s | F50: Male | G50: Rock
A51: =CONCATENATE(B51,C51) -> A Woman Like YouLee Brice | B51: A Woman Like You | C51: Lee Brice | D51: 2012 | E51: 2010s | F51: Male | G51: Country
A52: =CONCATENATE(B52,C52) -> AAWalker Hayes | B52: AA | C52: Walker Hayes | D52: 2022 | E52: 2020s | F52: Male | G52: Country
A53: =CONCATENATE(B53,C53) -> abcdefuGAYLE | B53: abcdefu | C53: GAYLE | D53: 2021 | E53: 2020s | F53: Female | G53: Pop | H53: Group Songs
A54: =CONCATENATE(B54,C54) -> About Damn TimeLizzo | B54: About Damn Time | C54: Lizzo | D54: 2022 | E54: 2020s | F54: Female | G54: Pop
A55: =CONCATENATE(B55,C55) -> According to YouOrianthi | B55: According to You | C55: Orianthi | D55: 2009 | E55: 2000s | F55: Female | G55: Pop, Rock
A56: =CONCATENATE(B56,C56) -> Ace in the HoleGeorge Strait | B56: Ace in the Hole | C56: George Strait | D56: 1989 | E56: 1980s | F56: Male | G56: Country
A57: =CONCATENATE(B57,C57) -> Ace of SpadesMotorhead | B57: Ace of Spades | C57: Motorhead | D57: 1980 | E57: 1980s | F57: Male | G57: Metal / Hard Rock | H57: Group Songs
A58: =CONCATENATE(B58,C58) -> Achy Breaky Song"Weird Al" Yankovic | B58: Achy Breaky Song | C58: "Weird Al" Yankovic | D58: 1993 | E58: 1990s | F58: Male | G58: Pop
A59: =CONCATENATE(B59,C59) -> Actin' UpMiranda Lambert | B59: Actin' Up | C59: Miranda Lambert | D59: 2022 | E59: 2020s | F59: Female | G59: Country
A60: =CONCATENATE(B60,C60) -> AddictedKelly Clarkson | B60: Addicted | C60: Kelly Clarkson | D60: 2004 | E60: 2000s | F60: Female | G60: Pop/Rock
A61: =CONCATENATE(B61,C61) -> Addicted to YouAvicii | B61: Addicted to You | C61: Avicii | D61: 2014 | E61: 2010s | F61: Female | G61: EDM/Pop
A62: =CONCATENATE(B62,C62) -> Adore YouHarry Styles | B62: Adore You | C62: Harry Styles | D62: 2019 | E62: 2010s | F62: Male | G62: Pop
A63: =CONCATENATE(B63,C63) -> AdornMiguel | B63: Adorn | C63: Miguel | D63: 2012 | E63: 2010s | F63: Male | G63: R&B
A64: =CONCATENATE(B64,C64) -> Adventure of a LifetimeColdplay | B64: Adventure of a Lifetime | C64: Coldplay | D64: 2015 | E64: 2010s | F64: Male | G64: Pop/Rock | H64: Group Songs
A65: =CONCATENATE(B65,C65) -> AerialsSystem of a Down | B65: Aerials | C65: System of a Down | D65: 2001 | E65: 2000s | F65: Male | G65: Metal / Hard Rock
A66: =CONCATENATE(B66,C66) -> AeroplaneRed Hot Chili Peppers | B66: Aeroplane | C66: Red Hot Chili Peppers | D66: 1995 | E66: 1990s | F66: Male | G66: Alternative / Indie
A67: =CONCATENATE(B67,C67) -> After DarkTito & Tarantula | B67: After Dark | C67: Tito & Tarantula | D67: 1996 | E67: 1990s | F67: Male | G67: Rock
A68: =CONCATENATE(B68,C68) -> After HoursThe Weeknd | B68: After Hours | C68: The Weeknd | D68: 2020 | E68: 2020s | F68: Male | G68: R&B
A69: =CONCATENATE(B69,C69) -> After the RainNelson | B69: After the Rain | C69: Nelson | D69: 1990 | E69: 1990s | F69: Male | G69: Rock
A70: =CONCATENATE(B70,C70) -> AfterlifeAvenged Sevenfold | B70: Afterlife | C70: Avenged Sevenfold | D70: 2007 | E70: 2000s | F70: Male | G70: Metal
A71: =CONCATENATE(B71,C71) -> AgainAlice in Chains | B71: Again | C71: Alice in Chains | D71: 1995 | E71: 1990s | F71: Male | G71: Alternative / Indie, Metal / Hard Rock
A72: =CONCATENATE(B72,C72) -> Ain't It FunParamore | B72: Ain't It Fun | C72: Paramore | D72: 2013 | E72: 2010s | F72: Female | G72: Pop/Rock | H72: Group Songs
A73: =CONCATENATE(B73,C73) -> Ain't No Grave (Gonna Hold My Body Down)Johnny Cash | B73: Ain't No Grave (Gonna Hold My Body Down) | C73: Johnny Cash | D73: 2010 | E73: 2010s | F73: Male | G73: Country/Gospel
A74: =CONCATENATE(B74,C74) -> Ain't No Love in OklahomaTwisters (2024 Film) | B74: Ain't No Love in Oklahoma | C74: Twisters (2024 Film) | D74: 2024 | E74: 2020s
A75: =CONCATENATE(B75,C75) -> Ain't No Rest for the WickedCage the Elephant | B75: Ain't No Rest for the Wicked | C75: Cage the Elephant | D75: 2008 | E75: 2000s | F75: Male | G75: Alternative/Rock
A76: =CONCATENATE(B76,C76) -> Ain't Always PrettyLogan Mize | B76: Ain't Always Pretty | C76: Logan Mize | D76: 2017 | E76: 2010s | F76: Male | G76: Country
A77: =CONCATENATE(B77,C77) -> Air GuitarMcBusted | B77: Air Guitar | C77: McBusted | D77: 2014 | E77: 2010s | F77: Male | G77: Pop, Rock | H77: Group Songs
A78: =CONCATENATE(B78,C78) -> AirplanesB.o.B ft. Hayley Williams | B78: Airplanes | C78: B.o.B ft. Hayley Williams | D78: 2010 | E78: 2010s | F78: Mixed | G78: Hip-Hop, Pop
A79: =CONCATENATE(B79,C79) -> AlbatrossCorrosion of Conformity | B79: Albatross | C79: Corrosion of Conformity | D79: 1994 | E79: 1990s | F79: Male | G79: Rock
A80: =CONCATENATE(B80,C80) -> AlejandroLady Gaga | B80: Alejandro | C80: Lady Gaga | D80: 2010 | E80: 2010s | F80: Female | G80: Pop
A81: =CONCATENATE(B81,C81) -> Alexander HamiltonHamilton Cast | B81: Alexander Hamilton | C81: Hamilton Cast | D81: 2015 | E81: 2010s | F81: Male | G81: Musical
A82: =CONCATENATE(B82,C82) -> AliveP.O.D. | B82: Alive | C82: P.O.D. | D82: 2001 | E82: 2000s | F82: Male | G82: Metal / Hard Rock
A83: =CONCATENATE(B83,C83) -> AliveSia | B83: Alive | C83: Sia | D83: 2015 | E83: 2010s | F83: Female | G83: Pop
A84: =CONCATENATE(B84,C84) -> All About That BassMeghan Trainor | B84: All About That Bass | C84: Meghan Trainor | D84: 2014 | E84: 2010s | F84: Female | G84: Pop | H84: Group Songs
A85: =CONCATENATE(B85,C85) -> All About That Bass (Explicit)Meghan Trainor | B85: All About That Bass (Explicit) | C85: Meghan Trainor | D85: 2014 | E85: 2010s | F85: Female | G85: Pop | H85: Group Songs
A86: =CONCATENATE(B86,C86) -> All About That Bass (with vocal)Meghan Trainor | B86: All About That Bass (with vocal) | C86: Meghan Trainor | D86: 2014 | E86: 2010s | F86: Female | G86: Pop | H86: Group Songs
A87: =CONCATENATE(B87,C87) -> All Along the WatchtowerU2 | B87: All Along the Watchtower | C87: U2 | D87: 1988 | E87: 1980s | F87: Male | G87: Rock
A88: =CONCATENATE(B88,C88) -> All Around MeFlyleaf | B88: All Around Me | C88: Flyleaf | D88: 2007 | E88: 2000s | F88: Female | G88: Alternative / Indie, Rock
A89: =CONCATENATE(B89,C89) -> All I AskAdele | B89: All I Ask | C89: Adele | D89: 2015 | E89: 2010s | F89: Female | G89: Pop
A90: =CONCATENATE(B90,C90) -> All I Care AboutChicago | B90: All I Care About | C90: Chicago | D90: 1975 | E90: 1970s | F90: Male | G90: Rock
A91: =CONCATENATE(B91,C91) -> All I Have to Do Is DreamThe Everly Brothers | B91: All I Have to Do Is Dream | C91: The Everly Brothers | D91: 1958 | E91: 1950s | F91: Male | G91: Pop
A92: =CONCATENATE(B92,C92) -> All I See Is YouShane Smith & The Saints | B92: All I See Is You | C92: Shane Smith & The Saints | D92: 2015 | E92: 2010s | F92: Male | G92: Country / Americana
A93: =CONCATENATE(B93,C93) -> All I WantThe Offspring | B93: All I Want | C93: The Offspring | D93: 1997 | E93: 1990s | F93: Male | G93: Punk Rock | H93: Group Songs
A94: =CONCATENATE(B94,C94) -> All I Want for Christmas Is My Two Front TeethSpike Jones & His City Slickers | B94: All I Want for Christmas Is My Two Front Teeth | C94: Spike Jones & His City Slickers | D94: 1948 | E94: 1940s | F94: Male | G94: Holiday, Comedy | H94: Group Songs
A95: =CONCATENATE(B95,C95) -> All I WantedParamore | B95: All I Wanted | C95: Paramore | D95: 2009 | E95: 2000s | F95: Female | G95: Alternative
A96: =CONCATENATE(B96,C96) -> All InChris Janson | B96: All In | C96: Chris Janson | D96: 2022 | E96: 2020s | F96: Male | G96: Country
A97: =CONCATENATE(B97,C97) -> All Kinds Of KindsMiranda Lambert | B97: All Kinds Of Kinds | C97: Miranda Lambert | D97: 2013 | E97: 2010s | F97: Female | G97: Country
A98: =CONCATENATE(B98,C98) -> All My Favorite PeopleMaren Morris ft. Brothers Osborne | B98: All My Favorite People | C98: Maren Morris ft. Brothers Osborne | D98: 2019 | E98: 2010s | F98: Mixed | G98: Country
A99: =CONCATENATE(B99,C99) -> All My LifeFoo Fighters | B99: All My Life | C99: Foo Fighters | D99: 2002 | E99: 2000s | F99: Male | G99: Rock
A100: =CONCATENATE(B100,C100) -> All Night LongRainbow | B100: All Night Long | C100: Rainbow | D100: 1979 | E100: 1970s | F100: Male | G100: Rock
A101: =CONCATENATE(B101,C101) -> All Night LongerSammy Adams | B101: All Night Longer | C101: Sammy Adams | D101: 2010 | E101: 2010s | F101: Male | G101: Hip-Hop
A102: =CONCATENATE(B102,C102) -> All of the StarsEd Sheeran | B102: All of the Stars | C102: Ed Sheeran | D102: 2014 | E102: 2010s | F102: Male | G102: Pop
A103: =CONCATENATE(B103,C103) -> All of YouEncanto (Cast) | B103: All of You | C103: Encanto (Cast) | D103: 2021 | E103: 2020s | F103: Mixed | G103: Musical/Disney
A104: =CONCATENATE(B104,C104) -> All Over the RoadEaston Corbin | B104: All Over the Road | C104: Easton Corbin | D104: 2012 | E104: 2010s | F104: Male | G104: Country
A105: =CONCATENATE(B105,C105) -> All Right NowFree | B105: All Right Now | C105: Free | D105: 1970 | E105: 1970s | F105: Male | G105: Rock | H105: Group Songs
A106: =CONCATENATE(B106,C106) -> All Signs Point to LauderdaleA Day to Remember | B106: All Signs Point to Lauderdale | C106: A Day to Remember | D106: 2010 | E106: 2010s | F106: Male | G106: Rock
A107: =CONCATENATE(B107,C107) -> All the Man That I NeedWhitney Houston | B107: All the Man That I Need | C107: Whitney Houston | D107: 1990 | E107: 1990s | F107: Female | G107: R&B
A108: =CONCATENATE(B108,C108) -> All the SameSick Puppies | B108: All the Same | C108: Sick Puppies | D108: 2006 | E108: 2000s | F108: Male | G108: Alternative / Indie
A109: =CONCATENATE(B109,C109) -> All Your LifeThe Band Perry | B109: All Your Life | C109: The Band Perry | D109: 2011 | E109: 2010s | F109: Female | G109: Country
A110: =CONCATENATE(B110,C110) -> All Your'nTyler Childers | B110: All Your'n | C110: Tyler Childers | D110: 2019 | E110: 2010s | F110: Male | G110: Country
A111: =CONCATENATE(B111,C111) -> Alligator SkyOwl City | B111: Alligator Sky | C111: Owl City | D111: 2011 | E111: 2010s | F111: Male | G111: Pop
A112: =CONCATENATE(B112,C112) -> AlmostBowling for Soup | B112: Almost | C112: Bowling for Soup | D112: 2005 | E112: 2000s | F112: Male | G112: Emo / Pop Punk
A113: =CONCATENATE(B113,C113) -> Almost (Sweet Music)Hozier | B113: Almost (Sweet Music) | C113: Hozier | D113: 2019 | E113: 2010s | F113: Male | G113: Indie/Pop
...

Sheet Totals
A1: Song listings at start | B1: 2681
A2: Final number of songs
A3: Hours worked

Sheet Final
A1: Unique ID | B1: title | C1: artist | D1: year | E1: decade | F1: original_vocal | G1: categories | H1: social_singing
A2: =CONCATENATE(B2,C2) -> 23Chayce Beckham | B2: 23 | C2: Chayce Beckham | D2: 2021 | E2: 2020s | F2: Male | G2: =VLOOKUP(A:A,Export!A:F,6,FALSE) -> Country
A3: =CONCATENATE(B3,C3) -> 23Sam Hunt | B3: 23 | C3: Sam Hunt | D3: 2021 | E3: 2020s | F3: Male | G3: =VLOOKUP(A:A,Export!A:F,6,FALSE) -> Country
A4: =CONCATENATE(B4,C4) -> 45Shinedown | B4: 45 | C4: Shinedown | D4: 2003 | E4: 2000s | F4: Male | G4: =VLOOKUP(A:A,Export!A:F,6,FALSE) -> Rock
A5: =CONCATENATE(B5,C5) -> 1985Bowling for Soup | B5: 1985 | C5: Bowling for Soup | D5: 2004 | E5: 2000s | F5: Male | G5: =VLOOKUP(A:A,Export!A:F,6,FALSE) -> Emo / Pop Punk | H5: =VLOOKUP(A:A,Export!A:G,7,FALSE) -> Group Songs
A6: =CONCATENATE(B6,C6) -> 3005Childish Gambino | B6: 3005 | C6: Childish Gambino | D6: 2013 | E6: 2010s | F6: Male | G6: =VLOOKUP(A:A,Export!A:F,6,FALSE) -> Hip-Hop
A7: =CONCATENATE(B7,C7) -> #SELFIEThe Chainsmokers | B7: #SELFIE | C7: The Chainsmokers | D7: 2014 | E7: 2010s | F7: Female | G7: =VLOOKUP(A:A,Export!A:F,6,FALSE) -> EDM / Pop
A8: =CONCATENATE(B8,C8) -> (I Can’t Get No) SatisfactionThe Rolling Stones | B8: (I Can’t Get No) Satisfaction | C8: The Rolling Stones | D8: 1965 | E8: 1960s | F8: Male | G8: =VLOOKUP(A:A,Export!A:F,6,FALSE) -> Rock | H8: =VLOOKUP(A:A,Export!A:G,7,FALSE) -> Group Songs
A9: =CONCATENATE(B9,C9) -> (Kissed You) Good NightGloriana | B9: (Kissed You) Good Night | C9: Gloriana | D9: 2012 | E9: 2010s | F9: Mixed | G9: =VLOOKUP(A:A,Export!A:F,6,FALSE) -> Country
A10: =CONCATENATE(B10,C10) -> (You Make Me Feel Like) A Natural WomanCarole King | B10: (You Make Me Feel Like) A Natural Woman | C10: Carole King | D10: 1971 | E10: 1970s | F10: Female | G10: =VLOOKUP(A:A,Export!A:F,6,FALSE) -> Soul / Pop
A11: =CONCATENATE(B11,C11) -> ’Til Summer Comes AroundKeith Urban | B11: ’Til Summer Comes Around | C11: Keith Urban | D11: 2009 | E11: 2000s | F11: Male | G11: =VLOOKUP(A:A,Export!A:F,6,FALSE) -> Country
A12: =CONCATENATE(B12,C12) -> ’Til You Can’tCody Johnson | B12: ’Til You Can’t | C12: Cody Johnson | D12: 2021 | E12: 2020s | F12: Male | G12: =VLOOKUP(A:A,Export!A:F,6,FALSE) -> Country
A13: =CONCATENATE(B13,C13) -> 0 to 100 / The Catch Up (Explicit)Drake | B13: 0 to 100 / The Catch Up (Explicit) | C13: Drake | D13: 2014 | E13: 2010s | F13: Male | G13: =VLOOKUP(A:A,Export!A:F,6,FALSE) -> Hip-Hop, Rap
A14: =CONCATENATE(B14,C14) -> 1, 2 ManyLuke Combs ft. Brooks & Dunn | B14: 1, 2 Many | C14: Luke Combs ft. Brooks & Dunn | D14: 2019 | E14: 2010s | F14: Male | G14: =VLOOKUP(A:A,Export!A:F,6,FALSE) -> Country
A15: =CONCATENATE(B15,C15) -> 1, 2, 3, 4Plain White T’s | B15: 1, 2, 3, 4 | C15: Plain White T’s | D15: 2008 | E15: 2000s | F15: Male | G15: =VLOOKUP(A:A,Export!A:F,6,FALSE) -> Pop
A16: =CONCATENATE(B16,C16) -> 10 Million PeopleExample | B16: 10 Million People | C16: Example | D16: 2014 | E16: 2010s | F16: Male | G16: =VLOOKUP(A:A,Export!A:F,6,FALSE) -> Pop
A17: =CONCATENATE(B17,C17) -> 10 Things I Hate About YouLeah Kate | B17: 10 Things I Hate About You | C17: Leah Kate | D17: 2022 | E17: 2020s | F17: Female | G17: =VLOOKUP(A:A,Export!A:F,6,FALSE) -> Pop
A18: =CONCATENATE(B18,C18) -> 10,000 HoursDan + Shay & Justin Bieber | B18: 10,000 Hours | C18: Dan + Shay & Justin Bieber | D18: 2019 | E18: 2010s | F18: Male | G18: =VLOOKUP(A:A,Export!A:F,6,FALSE) -> Pop/Country
A19: =CONCATENATE(B19,C19) -> 18 and LifeSkid Row | B19: 18 and Life | C19: Skid Row | D19: 1989 | E19: 1980s | F19: Male | G19: =VLOOKUP(A:A,Export!A:F,6,FALSE) -> Metal / Hard Rock
A20: =CONCATENATE(B20,C20) -> 1-800-273-8255Logic ft. Alessia Cara & Khalid | B20: 1-800-273-8255 | C20: Logic ft. Alessia Cara & Khalid | D20: 2017 | E20: 2010s | F20: Mixed | G20: =VLOOKUP(A:A,Export!A:F,6,FALSE) -> Hip-Hop
... A34: =CONCATENATE(B34,C34) -> 8 Second RideJake Owen | B34: 8 Second Ride | C34: Jake Owen | D34: 2006 | E34: 2000s | F34: Male | G34: =VLOOKUP(A:A,Export!A:F,6,FALSE) -> Country
A35: =CONCATENATE(B35,C35) -> 90’s CountryWalker Hayes | B35: 90’s Country | C35: Walker Hayes | D35: 2022 | E35: 2020s | F35: Male | G35: =VLOOKUP(A:A,Export!A:F,6,FALSE) -> Country | H35: =VLOOKUP(A:A,Export!A:G,7,FALSE) -> Group Songs
A36: =CONCATENATE(B36,C36) -> 99 LuftballonsNena | B36: 99 Luftballons | C36: Nena | D36: 1983 | E36: 1980s | F36: Female | G36: =VLOOKUP(A:A,Export!A:F,6,FALSE) -> Pop | H36: =VLOOKUP(A:A,Export!A:G,7,FALSE) -> Group Songs
A37: =CONCATENATE(B37,C37) -> A Bar Song (Tipsy)Shaboozey | B37: A Bar Song (Tipsy) | C37: Shaboozey | D37: 2024 | E37: 2020s | F37: Male | G37: =VLOOKUP(A:A,Export!A:F,6,FALSE) -> Country/Hip-Hop
A38: =CONCATENATE(B38,C38) -> A Billion GirlsElyar Fox | B38: A Billion Girls | C38: Elyar Fox | D38: 2014 | E38: 2010s | F38: Male | G38: =VLOOKUP(A:A,Export!A:F,6,FALSE) -> Pop
A39: =CONCATENATE(B39,C39) -> A Different WorldBucky Covington | B39: A Different World | C39: Bucky Covington | D39: 2007 | E39: 2000s | F39: Male | G39: =VLOOKUP(A:A,Export!A:F,6,FALSE) -> Country
A40: =CONCATENATE(B40,C40) -> A Good Hearted WomanLeAnn Rimes | B40: A Good Hearted Woman | C40: LeAnn Rimes | D40: 1999 | E40: 1990s | F40: Female | G40: =VLOOKUP(A:A,Export!A:F,6,FALSE) -> Country
A41: =CONCATENATE(B41,C41) -> A Guy Walks into a BarTyler Farr | B41: A Guy Walks into a Bar | C41: Tyler Farr | D41: 2015 | E41: 2010s | F41: Male | G41: =VLOOKUP(A:A,Export!A:F,6,FALSE) -> Country
A42: =CONCATENATE(B42,C42) -> A Little Bit OffFive Finger Death Punch | B42: A Little Bit Off | C42: Five Finger Death Punch | D42: 2020 | E42: 2020s | F42: Male | G42: =VLOOKUP(A:A,Export!A:F,6,FALSE) -> Rock
A43: =CONCATENATE(B43,C43) -> A Little Dive Bar in DahlonegaAshley McBryde | B43: A Little Dive Bar in Dahlonega | C43: Ashley McBryde | D43: 2017 | E43: 2010s | F43: Female | G43: =VLOOKUP(A:A,Export!A:F,6,FALSE) -> Country
A44: =CONCATENATE(B44,C44) -> A Little More SummertimeJason Aldean | B44: A Little More Summertime | C44: Jason Aldean | D44: 2016 | E44: 2010s | F44: Male | G44: =VLOOKUP(A:A,Export!A:F,6,FALSE) -> Country
A45: =CONCATENATE(B45,C45) -> A Little More YouLittle Big Town | B45: A Little More You | C45: Little Big Town | D45: 2007 | E45: 2000s | F45: Mixed | G45: =VLOOKUP(A:A,Export!A:F,6,FALSE) -> Country
A46: =CONCATENATE(B46,C46) -> A Love That Will LastRenee Olstead | B46: A Love That Will Last | C46: Renee Olstead | D46: 2004 | E46: 2000s | F46: Female | G46: =VLOOKUP(A:A,Export!A:F,6,FALSE) -> Jazz / Pop
A47: =CONCATENATE(B47,C47) -> A Million DreamsThe Greatest Showman Cast | B47: A Million Dreams | C47: The Greatest Showman Cast | D47: 2017 | E47: 2010s | F47: Mixed | G47: =VLOOKUP(A:A,Export!A:F,6,FALSE) -> Musical
A48: =CONCATENATE(B48,C48) -> A Quick Death in TexasClutch | B48: A Quick Death in Texas | C48: Clutch | D48: 2022 | E48: 2020s | F48: Male | G48: =VLOOKUP(A:A,Export!A:F,6,FALSE) -> Rock
A49: =CONCATENATE(B49,C49) -> A Sky Full of StarsColdplay | B49: A Sky Full of Stars | C49: Coldplay | D49: 2014 | E49: 2010s | F49: Male | G49: =VLOOKUP(A:A,Export!A:F,6,FALSE) -> Pop, Rock | H49: =VLOOKUP(A:A,Export!A:G,7,FALSE) -> Group Songs
A50: =CONCATENATE(B50,C50) -> A Symptom of Being HumanShinedown | B50: A Symptom of Being Human | C50: Shinedown | D50: 2022 | E50: 2020s | F50: Male | G50: =VLOOKUP(A:A,Export!A:F,6,FALSE) -> Rock
A51: =CONCATENATE(B51,C51) -> A Woman Like YouLee Brice | B51: A Woman Like You | C51: Lee Brice | D51: 2012 | E51: 2010s | F51: Male | G51: =VLOOKUP(A:A,Export!A:F,6,FALSE) -> Country
A52: =CONCATENATE(B52,C52) -> AAWalker Hayes | B52: AA | C52: Walker Hayes | D52: 2022 | E52: 2020s | F52: Male | G52: =VLOOKUP(A:A,Export!A:F,6,FALSE) -> Country
A53: =CONCATENATE(B53,C53) -> abcdefuGAYLE | B53: abcdefu | C53: GAYLE | D53: 2021 | E53: 2020s | F53: Female | G53: =VLOOKUP(A:A,Export!A:F,6,FALSE) -> Pop | H53: =VLOOKUP(A:A,Export!A:G,7,FALSE) -> Group Songs
A54: =CONCATENATE(B54,C54) -> About Damn TimeLizzo | B54: About Damn Time | C54: Lizzo | D54: 2022 | E54: 2020s | F54: Female | G54: =VLOOKUP(A:A,Export!A:F,6,FALSE) -> Pop
A55: =CONCATENATE(B55,C55) -> According to YouOrianthi | B55: According to You | C55: Orianthi | D55: 2009 | E55: 2000s | F55: Female | G55: =VLOOKUP(A:A,Export!A:F,6,FALSE) -> Pop, Rock
A56: =CONCATENATE(B56,C56) -> Ace in the HoleGeorge Strait | B56: Ace in the Hole | C56: George Strait | D56: 1989 | E56: 1980s | F56: Male | G56: =VLOOKUP(A:A,Export!A:F,6,FALSE) -> Country
A57: =CONCATENATE(B57,C57) -> Ace of SpadesMotörhead | B57: Ace of Spades | C57: Motörhead | D57: 1980 | E57: 1980s | F57: Male | G57: =VLOOKUP(A:A,Export!A:F,6,FALSE) -> Metal / Hard Rock | H57: =VLOOKUP(A:A,Export!A:G,7,FALSE) -> Group Songs
A58: =CONCATENATE(B58,C58) -> Achy Breaky Song“Weird Al” Yankovic | B58: Achy Breaky Song | C58: “Weird Al” Yankovic | D58: 1993 | E58: 1990s | F58: Male | G58: =VLOOKUP(A:A,Export!A:F,6,FALSE) -> Pop
A59: =CONCATENATE(B59,C59) -> Actin’ UpMiranda Lambert | B59: Actin’ Up | C59: Miranda Lambert | D59: 2022 | E59: 2020s | F59: Female | G59: =VLOOKUP(A:A,Export!A:F,6,FALSE) -> Country
A60: =CONCATENATE(B60,C60) -> AddictedKelly Clarkson | B60: Addicted | C60: Kelly Clarkson | D60: 2004 | E60: 2000s | F60: Female | G60: =VLOOKUP(A:A,Export!A:F,6,FALSE) -> Pop/Rock
A61: =CONCATENATE(B61,C61) -> Addicted to YouAvicii | B61: Addicted to You | C61: Avicii | D61: 2014 | E61: 2010s | F61: Female | G61: =VLOOKUP(A:A,Export!A:F,6,FALSE) -> EDM/Pop
A62: =CONCATENATE(B62,C62) -> Adore YouHarry Styles | B62: Adore You | C62: Harry Styles | D62: 2019 | E62: 2010s | F62: Male | G62: =VLOOKUP(A:A,Export!A:F,6,FALSE) -> Pop
A63: =CONCATENATE(B63,C63) -> AdornMiguel | B63: Adorn | C63: Miguel | D63: 2012 | E63: 2010s | F63: Male | G63: =VLOOKUP(A:A,Export!A:F,6,FALSE) -> R&B
A64: =CONCATENATE(B64,C64) -> Adventure of a LifetimeColdplay | B64: Adventure of a Lifetime | C64: Coldplay | D64: 2015 | E64: 2010s | F64: Male | G64: =VLOOKUP(A:A,Export!A:F,6,FALSE) -> Pop/Rock | H64: =VLOOKUP(A:A,Export!A:G,7,FALSE) -> Group Songs
A65: =CONCATENATE(B65,C65) -> AerialsSystem of a Down | B65: Aerials | C65: System of a Down | D65: 2001 | E65: 2000s | F65: Male | G65: =VLOOKUP(A:A,Export!A:F,6,FALSE) -> Metal / Hard Rock
A66: =CONCATENATE(B66,C66) -> AeroplaneRed Hot Chili Peppers | B66: Aeroplane | C66: Red Hot Chili Peppers | D66: 1995 | E66: 1990s | F66: Male | G66: =VLOOKUP(A:A,Export!A:F,6,FALSE) -> Alternative / Indie
A67: =CONCATENATE(B67,C67) -> After DarkTito & Tarantula | B67: After Dark | C67: Tito & Tarantula | D67: 1996 | E67: 1990s | F67: Male | G67: =VLOOKUP(A:A,Export!A:F,6,FALSE) -> Rock
A68: =CONCATENATE(B68,C68) -> After HoursThe Weeknd | B68: After Hours | C68: The Weeknd | D68: 2020 | E68: 2020s | F68: Male | G68: =VLOOKUP(A:A,Export!A:F,6,FALSE) -> R&B
A69: =CONCATENATE(B69,C69) -> After the RainNelson | B69: After the Rain | C69: Nelson | D69: 1990 | E69: 1990s | F69: Male | G69: =VLOOKUP(A:A,Export!A:F,6,FALSE) -> Rock
A70: =CONCATENATE(B70,C70) -> AfterlifeAvenged Sevenfold | B70: Afterlife | C70: Avenged Sevenfold | D70: 2007 | E70: 2000s | F70: Male | G70: =VLOOKUP(A:A,Export!A:F,6,FALSE) -> Metal
A71: =CONCATENATE(B71,C71) -> AgainAlice in Chains | B71: Again | C71: Alice in Chains | D71: 1995 | E71: 1990s | F71: Male | G71: =VLOOKUP(A:A,Export!A:F,6,FALSE) -> Alternative / Indie, Metal / Hard Rock
A72: =CONCATENATE(B72,C72) -> Ain’t It FunParamore | B72: Ain’t It Fun | C72: Paramore | D72: 2013 | E72: 2010s | F72: Female | G72: =VLOOKUP(A:A,Export!A:F,6,FALSE) -> Pop/Rock | H72: =VLOOKUP(A:A,Export!A:G,7,FALSE) -> Group Songs
A73: =CONCATENATE(B73,C73) -> Ain’t No Grave (Gonna Hold My Body Down)Johnny Cash | B73: Ain’t No Grave (Gonna Hold My Body Down) | C73: Johnny Cash | D73: 2010 | E73: 2010s | F73: Male | G73: =VLOOKUP(A:A,Export!A:F,6,FALSE) -> Country/Gospel
A74: =CONCATENATE(B74,C74) -> Ain’t No Love in OklahomaTwisters (2024 Film) | B74: Ain’t No Love in Oklahoma | C74: Twisters (2024 Film) | D74: 2024 | E74: 2020s
A75: =CONCATENATE(B75,C75) -> Ain’t No Rest for the WickedCage the Elephant | B75: Ain’t No Rest for the Wicked | C75: Cage the Elephant | D75: 2008 | E75: 2000s | F75: Male | G75: =VLOOKUP(A:A,Export!A:F,6,FALSE) -> Alternative/Rock
A76: =CONCATENATE(B76,C76) -> Ain't Always PrettyLogan Mize | B76: Ain't Always Pretty | C76: Logan Mize | D76: 2017 | E76: 2010s | F76: Male | G76: =VLOOKUP(A:A,Export!A:F,6,FALSE) -> Country
A77: =CONCATENATE(B77,C77) -> Air GuitarMcBusted | B77: Air Guitar | C77: McBusted | D77: 2014 | E77: 2010s | F77: Male | G77: =VLOOKUP(A:A,Export!A:F,6,FALSE) -> Pop, Rock | H77: =VLOOKUP(A:A,Export!A:G,7,FALSE) -> Group Songs
A78: =CONCATENATE(B78,C78) -> AirplanesB.o.B ft. Hayley Williams | B78: Airplanes | C78: B.o.B ft. Hayley Williams | D78: 2010 | E78: 2010s | F78: Mixed | G78: =VLOOKUP(A:A,Export!A:F,6,FALSE) -> Hip-Hop, Pop
A79: =CONCATENATE(B79,C79) -> AlbatrossCorrosion of Conformity | B79: Albatross | C79: Corrosion of Conformity | D79: 1994 | E79: 1990s | F79: Male | G79: =VLOOKUP(A:A,Export!A:F,6,FALSE) -> Rock
A80: =CONCATENATE(B80,C80) -> AlejandroLady Gaga | B80: Alejandro | C80: Lady Gaga | D80: 2010 | E80: 2010s | F80: Female | G80: =VLOOKUP(A:A,Export!A:F,6,FALSE) -> Pop
A81: =CONCATENATE(B81,C81) -> Alexander HamiltonHamilton Cast | B81: Alexander Hamilton | C81: Hamilton Cast | D81: 2015 | E81: 2010s | F81: Male | G81: =VLOOKUP(A:A,Export!A:F,6,FALSE) -> Musical
A82: =CONCATENATE(B82,C82) -> AliveP.O.D. | B82: Alive | C82: P.O.D. | D82: 2001 | E82: 2000s | F82: Male | G82: =VLOOKUP(A:A,Export!A:F,6,FALSE) -> Metal / Hard Rock
A83: =CONCATENATE(B83,C83) -> AliveSia | B83: Alive | C83: Sia | D83: 2015 | E83: 2010s | F83: Female | G83: =VLOOKUP(A:A,Export!A:F,6,FALSE) -> Pop
A84: =CONCATENATE(B84,C84) -> All About That BassMeghan Trainor | B84: All About That Bass | C84: Meghan Trainor | D84: 2014 | E84: 2010s | F84: Female | G84: =VLOOKUP(A:A,Export!A:F,6,FALSE) -> Pop | H84: =VLOOKUP(A:A,Export!A:G,7,FALSE) -> Group Songs
A85: =CONCATENATE(B85,C85) -> All About That Bass (Explicit)Meghan Trainor | B85: All About That Bass (Explicit) | C85: Meghan Trainor | D85: 2014 | E85: 2010s | F85: Female | G85: =VLOOKUP(A:A,Export!A:F,6,FALSE) -> Pop | H85: =VLOOKUP(A:A,Export!A:G,7,FALSE) -> Group Songs
A86: =CONCATENATE(B86,C86) -> All About That Bass (with vocal)Meghan Trainor | B86: All About That Bass (with vocal) | C86: Meghan Trainor | D86: 2014 | E86: 2010s | F86: Female | G86: =VLOOKUP(A:A,Export!A:F,6,FALSE) -> Pop | H86: =VLOOKUP(A:A,Export!A:G,7,FALSE) -> Group Songs
A87: =CONCATENATE(B87,C87) -> All Along the WatchtowerU2 | B87: All Along the Watchtower | C87: U2 | D87: 1988 | E87: 1980s | F87: Male | G87: =VLOOKUP(A:A,Export!A:F,6,FALSE) -> Rock
A88: =CONCATENATE(B88,C88) -> All Around MeFlyleaf | B88: All Around Me | C88: Flyleaf | D88: 2007 | E88: 2000s | F88: Female | G88: =VLOOKUP(A:A,Export!A:F,6,FALSE) -> Alternative / Indie, Rock
A89: =CONCATENATE(B89,C89) -> All I AskAdele | B89: All I Ask | C89: Adele | D89: 2015 | E89: 2010s | F89: Female | G89: =VLOOKUP(A:A,Export!A:F,6,FALSE) -> Pop
A90: =CONCATENATE(B90,C90) -> All I Care AboutChicago | B90: All I Care About | C90: Chicago | D90: 1975 | E90: 1970s | F90: Male | G90: =VLOOKUP(A:A,Export!A:F,6,FALSE) -> Rock
A91: =CONCATENATE(B91,C91) -> All I Have to Do Is DreamThe Everly Brothers | B91: All I Have to Do Is Dream | C91: The Everly Brothers | D91: 1958 | E91: 1950s | F91: Male | G91: =VLOOKUP(A:A,Export!A:F,6,FALSE) -> Pop
A92: =CONCATENATE(B92,C92) -> All I See Is YouShane Smith & The Saints | B92: All I See Is You | C92: Shane Smith & The Saints | D92: 2015 | E92: 2010s | F92: Male | G92: =VLOOKUP(A:A,Export!A:F,6,FALSE) -> Country / Americana
A93: =CONCATENATE(B93,C93) -> All I WantThe Offspring | B93: All I Want | C93: The Offspring | D93: 1997 | E93: 1990s | F93: Male | G93: =VLOOKUP(A:A,Export!A:F,6,FALSE) -> Punk Rock | H93: =VLOOKUP(A:A,Export!A:G,7,FALSE) -> Group Songs
A94: =CONCATENATE(B94,C94) -> All I Want for Christmas Is My Two Front TeethSpike Jones & His City Slickers | B94: All I Want for Christmas Is My Two Front Teeth | C94: Spike Jones & His City Slickers | D94: 1948 | E94: 1940s | F94: Male | G94: =VLOOKUP(A:A,Export!A:F,6,FALSE) -> Holiday, Comedy | H94: =VLOOKUP(A:A,Export!A:G,7,FALSE) -> Group Songs
A95: =CONCATENATE(B95,C95) -> All I WantedParamore | B95: All I Wanted | C95: Paramore | D95: 2009 | E95: 2000s | F95: Female | G95: =VLOOKUP(A:A,Export!A:F,6,FALSE) -> Alternative
A96: =CONCATENATE(B96,C96) -> All InChris Janson | B96: All In | C96: Chris Janson | D96: 2022 | E96: 2020s | F96: Male | G96: =VLOOKUP(A:A,Export!A:F,6,FALSE) -> Country
A97: =CONCATENATE(B97,C97) -> All Kinds Of KindsMiranda Lambert | B97: All Kinds Of Kinds | C97: Miranda Lambert | D97: 2013 | E97: 2010s | F97: Female | G97: =VLOOKUP(A:A,Export!A:F,6,FALSE) -> Country
A98: =CONCATENATE(B98,C98) -> All My Favorite PeopleMaren Morris ft. Brothers Osborne | B98: All My Favorite People | C98: Maren Morris ft. Brothers Osborne | D98: 2019 | E98: 2010s | F98: Mixed | G98: =VLOOKUP(A:A,Export!A:F,6,FALSE) -> Country
A99: =CONCATENATE(B99,C99) -> All My LifeFoo Fighters | B99: All My Life | C99: Foo Fighters | D99: 2002 | E99: 2000s | F99: Male | G99: =VLOOKUP(A:A,Export!A:F,6,FALSE) -> Rock
A100: =CONCATENATE(B100,C100) -> All Night LongRainbow | B100: All Night Long | C100: Rainbow | D100: 1979 | E100: 1970s | F100: Male | G100: =VLOOKUP(A:A,Export!A:F,6,FALSE) -> Rock
A101: =CONCATENATE(B101,C101) -> All Night LongerSammy Adams | B101: All Night Longer | C101: Sammy Adams | D101: 2010 | E101: 2010s | F101: Male | G101: =VLOOKUP(A:A,Export!A:F,6,FALSE) -> Hip-Hop
A102: =CONCATENATE(B102,C102) -> All of the StarsEd Sheeran | B102: All of the Stars | C102: Ed Sheeran | D102: 2014 | E102: 2010s | F102: Male | G102: =VLOOKUP(A:A,Export!A:F,6,FALSE) -> Pop
A103: =CONCATENATE(B103,C103) -> All of YouEncanto (Cast) | B103: All of You | C103: Encanto (Cast) | D103: 2021 | E103: 2020s | F103: Mixed | G103: =VLOOKUP(A:A,Export!A:F,6,FALSE) -> Musical/Disney
A104: =CONCATENATE(B104,C104) -> All Over the RoadEaston Corbin | B104: All Over the Road | C104: Easton Corbin | D104: 2012 | E104: 2010s | F104: Male | G104: =VLOOKUP(A:A,Export!A:F,6,FALSE) -> Country
A105: =CONCATENATE(B105,C105) -> All Right NowFree | B105: All Right Now | C105: Free | D105: 1970 | E105: 1970s | F105: Male | G105: =VLOOKUP(A:A,Export!A:F,6,FALSE) -> Rock | H105: =VLOOKUP(A:A,Export!A:G,7,FALSE) -> Group Songs
A106: =CONCATENATE(B106,C106) -> All Signs Point to LauderdaleA Day to Remember | B106: All Signs Point to Lauderdale | C106: A Day to Remember | D106: 2010 | E106: 2010s | F106: Male | G106: =VLOOKUP(A:A,Export!A:F,6,FALSE) -> Rock
A107: =CONCATENATE(B107,C107) -> All the Man That I NeedWhitney Houston | B107: All the Man That I Need | C107: Whitney Houston | D107: 1990 | E107: 1990s | F107: Female | G107: =VLOOKUP(A:A,Export!A:F,6,FALSE) -> R&B
A108: =CONCATENATE(B108,C108) -> All the SameSick Puppies | B108: All the Same | C108: Sick Puppies | D108: 2006 | E108: 2000s | F108: Male | G108: =VLOOKUP(A:A,Export!A:F,6,FALSE) -> Alternative / Indie
A109: =CONCATENATE(B109,C109) -> All Your LifeThe Band Perry | B109: All Your Life | C109: The Band Perry | D109: 2011 | E109: 2010s | F109: Female | G109: =VLOOKUP(A:A,Export!A:F,6,FALSE) -> Country
A110: =CONCATENATE(B110,C110) -> All Your’nTyler Childers | B110: All Your’n | C110: Tyler Childers | D110: 2019 | E110: 2010s | F110: Male | G110: =VLOOKUP(A:A,Export!A:F,6,FALSE) -> Country
A111: =CONCATENATE(B111,C111) -> Alligator SkyOwl City | B111: Alligator Sky | C111: Owl City | D111: 2011 | E111: 2010s | F111: Male | G111: =VLOOKUP(A:A,Export!A:F,6,FALSE) -> Pop
A112: =CONCATENATE(B112,C112) -> AlmostBowling for Soup | B112: Almost | C112: Bowling for Soup | D112: 2005 | E112: 2000s | F112: Male | G112: =VLOOKUP(A:A,Export!A:F,6,FALSE) -> Emo / Pop Punk
A113: =CONCATENATE(B113,C113) -> Almost (Sweet Music)Hozier | B113: Almost (Sweet Music) | C113: Hozier | D113: 2019 | E113: 2010s | F113: Male | G113: =VLOOKUP(A:A,Export!A:F,6,FALSE) -> Indie/Pop
...

Sheet Export
A1: Unique ID | B1: title | C1: artist | D1: year | E1: decade | F1: categories | G1: social_singing | H1: original_vocal | I1: possible_duplicate | J1: match_confidence | K1: needs_review | L1: notes | M1: raw_input
A2: =CONCATENATE(B2,C2) -> Word Crimes"Weird Al" Yankovic | B2: Word Crimes | C2: "Weird Al" Yankovic | D2: 2014 | E2: 2010s | F2: Novelty / Comedy, Pop | G2: Group Songs | H2: Male | J2: High | L2: corrected artist spelling | M2: G28959 - Word Crimes - Weird Al Yankovich.cdg
A3: =CONCATENATE(B3,C3) -> 10 Million PeopleExample | B3: 10 Million People | C3: Example | D3: 2014 | E3: 2010s | F3: Pop | H3: Male | J3: High | L3: removed catalog code and file extension | M3: SF344-11 - Example - 10 Million People.cdg
A4: =CONCATENATE(B4,C4) -> A Sky Full of StarsColdplay | B4: A Sky Full of Stars | C4: Coldplay | D4: 2014 | E4: 2010s | F4: Pop, Rock | G4: Group Songs | H4: Male | J4: High | L4: corrected title to standard release form
A5: =CONCATENATE(B5,C5) -> She Looks So Perfect5 Seconds of Summer | B5: She Looks So Perfect | C5: 5 Seconds of Summer | D5: 2014 | E5: 2010s | F5: Pop, Rock | G5: Group Songs | H5: Male | J5: High | L5: normalized artist styling | M5: KCDPR1408-02 - 5 Seconds Of Summer - She Looks So Perfect.cdg
A6: =CONCATENATE(B6,C6) -> Play BallAC/DC | B6: Play Ball | C6: AC/DC | D6: 2014 | E6: 2010s | F6: Rock | H6: Male | I6: Possible Duplicate | J6: High | L6: variant version present | M6: DFK091-05 - AC-DC - Play Ball (Wbgv).zip
A7: =CONCATENATE(B7,C7) -> Play Ball (with vocal)AC/DC | B7: Play Ball (with vocal) | C7: AC/DC | D7: 2014 | E7: 2010s | F7: Rock | H7: Male | J7: High | M7: DFK091-04 - AC-DC - Play Ball (Wvocal).zip
A8: =CONCATENATE(B8,C8) -> It's On AgainAlicia Keys feat. Kendrick Lamar | B8: It's On Again | C8: Alicia Keys feat. Kendrick Lamar | D8: 2014 | E8: 2010s | F8: R&B, Pop | H8: Female | J8: High | L8: normalized featured artist formatting | M8: MRH117-16 - Alicia Keys Ft Kendrick Lamar - It's On Again.cdg
A9: =CONCATENATE(B9,C9) -> BelieverAmerican Authors | B9: Believer | C9: American Authors | D9: 2014 | E9: 2010s | F9: Alternative / Indie, Rock | G9: Group Songs | H9: Male | J9: High | L9: removed catalog code and file extension | M9: KCDPR1408-04 - American Authors - Believer.cdg
A10: =CONCATENATE(B10,C10) -> Snap Out of ItArctic Monkeys | B10: Snap Out of It | C10: Arctic Monkeys | D10: 2013 | E10: 2010s | F10: Rock, Alternative / Indie | H10: Male | J10: High | L10: normalized title capitalization | M10: SF341-03 - Arctic Monkeys - Snap Out Of It.cdg
A11: =CONCATENATE(B11,C11) -> All About That BassMeghan Trainor | B11: All About That Bass | C11: Meghan Trainor | D11: 2014 | E11: 2010s | F11: Pop | G11: Group Songs | H11: Female | J11: High
A12: =CONCATENATE(B12,C12) -> Break FreeAriana Grande feat. Zedd | B12: Break Free | C12: Ariana Grande feat. Zedd | D12: 2014 | E12: 2010s | F12: Pop, Dance / Disco | G12: Group Songs | H12: Female | J12: High | L12: normalized featured artist formatting | M12: MRH119-17 - Ariana Grande Ft Zedd - Break Free.cdg
A13: =CONCATENATE(B13,C13) -> Lay Me DownAvicii feat. Adam Lambert | B13: Lay Me Down | C13: Avicii feat. Adam Lambert | D13: 2014 | E13: 2010s | F13: Dance / Disco, Pop | G13: Group Songs | H13: Male | J13: High | L13: normalized featured artist formatting | M13: MRH119-11 - Avicii Ft Adam Lambert - Lay Me Down.cdg
A14: =CONCATENATE(B14,C14) -> Am I WrongNico & Vinz | B14: Am I Wrong | C14: Nico & Vinz | D14: 2013 | E14: 2010s | F14: Pop | G14: Group Songs | H14: Male | J14: High | L14: removed catalog code and file extension
A15: =CONCATENATE(B15,C15) -> ShowerBecky G | B15: Shower | C15: Becky G | D15: 2014 | E15: 2010s | F15: Pop | G15: Group Songs | H15: Female | J15: High | L15: removed catalog code and file extension | M15: G28922 - Shower - Becky G.cdg
A16: =CONCATENATE(B16,C16) -> Mine (Explicit)Beyoncé feat. Drake | B16: Mine (Explicit) | C16: Beyoncé feat. Drake | D16: 2013 | E16: 2010s | F16: R&B, Pop | H16: Female | J16: High | L16: removed catalog code and file extension | M16: G28440 - Mine (explicit) - Beyonce feat. Drake.cdg
A17: =CONCATENATE(B17,C17) -> 23 Degrees and SouthBilly Currington | B17: 23 Degrees and South | C17: Billy Currington | D17: 2013 | E17: 2010s | F17: Country | H17: Male | J17: High | L17: normalized title capitalization | M17: KCD1408-02 - Billy Currington - 23 Degrees And South.cdg
A18: =CONCATENATE(B18,C18) -> Neon LightBlake Shelton | B18: Neon Light | C18: Blake Shelton | D18: 2014 | E18: 2010s | F18: Country | H18: Male | I18: Possible Duplicate | J18: High | L18: variant version present | M18: DFK091-02 - Blake Shelton - Neon Light (Wbgv).zip
A19: =CONCATENATE(B19,C19) -> Neon Light (with vocal)Blake Shelton | B19: Neon Light (with vocal) | C19: Blake Shelton | D19: 2014 | E19: 2010s | F19: Country | H19: Male | J19: High | M19: DFK091-01 - Blake Shelton - Neon Light (Wvocal).zip
A20: =CONCATENATE(B20,C20) -> MuttBlink-182 | B20: Mutt | C20: Blink-182 | D20: 1999 | E20: 90s | F20: Punk, Rock | H20: Male | J20: High | L20: cleaned filename junk | M20: Blink_182_Mutt(MP3+CDG_Karaoke)_10964551.zip
A21: =CONCATENATE(B21,C21) -> High School Never EndsBowling for Soup | B21: High School Never Ends | C21: Bowling for Soup | D21: 2006 | E21: 2000s | F21: Emo / Pop Punk | G21: Group Songs | H21: Male | J21: High | M21: Bowling_for_Soup_High_School_Never_Ends(MP3+CDG_Karaoke)_10558576.zip
A22: =CONCATENATE(B22,C22) -> One Minute MoreCapital Cities | B22: One Minute More | C22: Capital Cities | D22: 2014 | E22: 2010s | F22: Pop, Alternative / Indie | H22: Male | J22: High | L22: removed catalog code and file extension | M22: KCDPR1408-05 - Capital Cities - One Minute More.cdg
A23: =CONCATENATE(B23,C23) -> Amnesia5 Seconds of Summer | B23: Amnesia | C23: 5 Seconds of Summer | D23: 2014 | E23: 2010s | F23: Pop, Rock | G23: Group Songs | H23: Male | J23: High | L23: normalized artist styling
A24: =CONCATENATE(B24,C24) -> LightningCash Cash feat. John Rzeznik | B24: Lightning | C24: Cash Cash feat. John Rzeznik | D24: 2014 | E24: 2010s | F24: Dance / Disco, Pop | H24: Male | J24: High | L24: normalized featured artist formatting | M24: KCDPR1408-06 - Cash Cash & John Rzeznik - Lightning.cdg
A25: =CONCATENATE(B25,C25) -> I Don’t Know Why I Love You But I DoCharley Pride | B25: I Don’t Know Why I Love You But I Do | C25: Charley Pride | D25: 1972 | E25: 70s | F25: Country | H25: Male | I25: Possible Duplicate | J25: High | L25: variant version present | M25: DFK091-08 - Charley Pride - I Don't Know Why I Love You But I Do (Wbgv).zip
A26: =CONCATENATE(B26,C26) -> I Don’t Know Why I Love You But I Do (with vocal)Charley Pride | B26: I Don’t Know Why I Love You But I Do (with vocal) | C26: Charley Pride | D26: 1972 | E26: 70s | F26: Country | H26: Male | J26: High | M26: DFK091-07 - Charley Pride - I Don't Know Why I Love You But I Do (Wvocal).zip
A27: =CONCATENATE(B27,C27) -> Boom ClapCharli XCX | B27: Boom Clap | C27: Charli XCX | D27: 2014 | E27: 2010s | F27: Pop | G27: Group Songs | H27: Female | J27: High | L27: normalized artist spelling | M27: G28870 - Boom Clap - Charlie XCX.cdg
A28: =CONCATENATE(B28,C28) -> Ready Set RollChase Rice | B28: Ready Set Roll | C28: Chase Rice | D28: 2014 | E28: 2010s | F28: Country | H28: Male | J28: High | L28: reversed order fixed | M28: A28546 - Ready Set Roll - Chase Rice.cdg
A29: =CONCATENATE(B29,C29) -> StampedeChris LeDoux | B29: Stampede | C29: Chris LeDoux | D29: 1993 | E29: 90s | F29: Country | H29: Male | J29: High | M29: Chris_LeDoux_Stampede(MP3+CDG_Karaoke)_10405499.zip
A30: =CONCATENATE(B30,C30) -> AnacondaNicki Minaj | B30: Anaconda | C30: Nicki Minaj | D30: 2014 | E30: 2010s | F30: Hip-Hop, Rap | H30: Female | J30: High | L30: removed catalog code and file extension
A31: =CONCATENATE(B31,C31) -> Travelin’ SoldierCody Johnson | B31: Travelin’ Soldier | C31: Cody Johnson | D31: 2019 | E31: 2010s | F31: Country | H31: Male | J31: Medium | K31: Yes | L31: cover vs original (Dixie Chicks) | M31: Cody_Johnson_Travelin_Soldier(MP3+CDG_Karaoke)_10989200.zip
A32: =CONCATENATE(B32,C32) -> Drivin’ Around SongColt Ford ft. Jason Aldean | B32: Drivin’ Around Song | C32: Colt Ford ft. Jason Aldean | D32: 2013 | E32: 2010s | F32: Country | H32: Male | J32: High | L32: kept feature | M32: ASK1209C-02 - Colt Ford & Jason Aldean - Drivin' Around Song.zip
A33: =CONCATENATE(B33,C33) -> Bad BloodBastille | B33: Bad Blood | C33: Bastille | D33: 2013 | E33: 2010s | F33: Alternative / Indie, Pop | G33: Group Songs | H33: Male | J33: High | L33: removed catalog code and file extension
A34: =CONCATENATE(B34,C34) -> Outta My HeadCraig Campbell | B34: Outta My Head | C34: Craig Campbell | D34: 2012 | E34: 2010s | F34: Country | H34: Male | J34: High | M34: ASK1209C-04 - Craig Campbell - Outta My Head.zip
A35: =CONCATENATE(B35,C35) -> Young in AmericaDanielle Bradbery | B35: Young in America | C35: Danielle Bradbery | D35: 2014 | E35: 2010s | F35: Country | H35: Female | J35: High | L35: normalized title capitalization | M35: KCD1408-03 - Danielle Bradbery - Young In America.cdg
A36: =CONCATENATE(B36,C36) -> True BelieversDarius Rucker | B36: True Believers | C36: Darius Rucker | D36: 2013 | E36: 2010s | F36: Country | H36: Male | J36: High | M36: ASK1209C-09 - Darius Rucker - True Believers.zip
A37: =CONCATENATE(B37,C37) -> Shot Me DownDavid Guetta feat. Skylar Grey | B37: Shot Me Down | C37: David Guetta feat. Skylar Grey | D37: 2014 | E37: 2010s | F37: Dance / Disco, Pop | H37: Male | J37: High | L37: normalized featured artist formatting | M37: KCD1407-2-03 - David Guetta & Skylar Grey - Shot Me Down.cdg
A38: =CONCATENATE(B38,C38) -> Neon LightsDemi Lovato | B38: Neon Lights | C38: Demi Lovato | D38: 2013 | E38: 2010s | F38: Pop, Dance / Disco | H38: Female | J38: High | L38: removed catalog code and file extension | M38: SF341-17 - Demi Lovato - Neon Lights.cdg
A39: =CONCATENATE(B39,C39) -> Really Don't CareDemi Lovato feat. Cher Lloyd | B39: Really Don't Care | C39: Demi Lovato feat. Cher Lloyd | D39: 2014 | E39: 2010s | F39: Pop | G39: Group Songs | H39: Female | J39: High | L39: normalized featured artist formatting | M39: KCDPR1408-10 - Demi Lovato & Cher Lloyd - Really Don't Care.cdg
A40: =CONCATENATE(B40,C40) -> Country & Cold CansDierks Bentley | B40: Country & Cold Cans | C40: Dierks Bentley | D40: 2012 | E40: 2010s | F40: Country | H40: Male | J40: High | M40: ASK1209C-01 - Dierks Bentley - Country & Cold Cans.zip
A41: =CONCATENATE(B41,C41) -> Drunk on a PlaneDierks Bentley | B41: Drunk on a Plane | C41: Dierks Bentley | D41: 2014 | E41: 2010s | F41: Country | G41: Group Songs | H41: Male | J41: High | M41: ASK1408-07 - Dierks Bentley - Drunk On A Plane.cdg
A42: =CONCATENATE(B42,C42) -> Drunk on a Plane (with vocal)Dierks Bentley | B42: Drunk on a Plane (with vocal) | C42: Dierks Bentley | D42: 2014 | E42: 2010s | F42: Country | G42: Group Songs | H42: Male | J42: High | L42: kept alt vocal version | M42: ASK1408-15 - Dierks Bentley - Drunk On A Plane Wvocal.cdg
A43: =CONCATENATE(B43,C43) -> BailandoEnrique Iglesias feat. Sean Paul | B43: Bailando | C43: Enrique Iglesias feat. Sean Paul | D43: 2014 | E43: 2010s | F43: Pop, Dance / Disco | G43: Group Songs | H43: Male | J43: Medium | K43: Yes | L43: removed non-standard version tag "English version"; multiple release/version variants
A44: =CONCATENATE(B44,C44) -> BailandoEnrique Iglesias feat. Sean Paul, Gente de Zona & Descemer Bueno | B44: Bailando | C44: Enrique Iglesias feat. Sean Paul, Gente de Zona & Descemer Bueno | D44: 2014 | E44: 2010s | F44: Pop, Dance / Disco | G44: Group Songs | H44: Male | J44: Medium | K44: Yes | L44: multiple featured artists; version may vary
A45: =CONCATENATE(B45,C45) -> Make U BounceDJ Fresh vs TC | B45: Make U Bounce | C45: DJ Fresh vs TC | D45: 2014 | E45: 2010s | F45: Dance / Disco | H45: Male | J45: Medium | K45: Yes | L45: collaboration styling may vary by release | M45: MRH119-06 - DJ Fresh Vs TC - Make U Bounce.cdg
A46: =CONCATENATE(B46,C46) -> 0 to 100 / The Catch Up (Explicit)Drake | B46: 0 to 100 / The Catch Up (Explicit) | C46: Drake | D46: 2014 | E46: 2010s | F46: Hip-Hop, Rap | H46: Male | J46: High | L46: normalized title punctuation | M46: G28973 - 0 to 100 - The Catch Up (explicit) - Drake.cdg
A47: =CONCATENATE(B47,C47) -> Worst BehaviorDrake | B47: Worst Behavior | C47: Drake | D47: 2013 | E47: 2010s | F47: Hip-Hop, Rap | H47: Male | J47: High | L47: removed catalog code and file extension | M47: KCD1407-2-01 - Drake - Worst Behavior.cdg
A48: =CONCATENATE(B48,C48) -> All of the StarsEd Sheeran | B48: All of the Stars | C48: Ed Sheeran | D48: 2014 | E48: 2010s | F48: Pop | H48: Male | J48: High | L48: normalized title capitalization | M48: MRH118-02 - Ed Sheeran - All Of The Stars.cdg
A49: =CONCATENATE(B49,C49) -> Bang BangJessie J feat. Ariana Grande & Nicki Minaj | B49: Bang Bang | C49: Jessie J feat. Ariana Grande & Nicki Minaj | D49: 2014 | E49: 2010s | F49: Pop | G49: Group Songs | H49: Female | J49: High | L49: normalized featured artist formatting
A50: =CONCATENATE(B50,C50) -> Beating HeartEllie Goulding | B50: Beating Heart | C50: Ellie Goulding | D50: 2014 | E50: 2010s | F50: Pop | H50: Female | J50: High | L50: removed catalog code and file extension
A51: =CONCATENATE(B51,C51) -> Thinking Out LoudEd Sheeran | B51: Thinking Out Loud | C51: Ed Sheeran | D51: 2014 | E51: 2010s | F51: Pop | G51: Group Songs | H51: Male | J51: High | L51: removed catalog code and file extension | M51: G28920 - Thinking Out Loud - Ed Sheeran.cdg
A52: =CONCATENATE(B52,C52) -> Say GoodnightEli Young Band | B52: Say Goodnight | C52: Eli Young Band | D52: 2012 | E52: 2010s | F52: Country | H52: Male | J52: High | M52: ASK1209C-07 - Eli Young Band - Say Goodnight.zip
A53: =CONCATENATE(B53,C53) -> BirthdayKaty Perry | B53: Birthday | C53: Katy Perry | D53: 2013 | E53: 2010s | F53: Pop | G53: Group Songs | H53: Female | J53: High | L53: removed catalog code and file extension
A54: =CONCATENATE(B54,C54) -> Black WidowIggy Azalea feat. Rita Ora | B54: Black Widow | C54: Iggy Azalea feat. Rita Ora | D54: 2014 | E54: 2010s | F54: Hip-Hop, Rap, Pop | G54: Group Songs | H54: Female | J54: High | L54: normalized featured artist formatting
A55: =CONCATENATE(B55,C55) -> A Billion GirlsElyar Fox | B55: A Billion Girls | C55: Elyar Fox | D55: 2014 | E55: 2010s | F55: Pop | H55: Male | J55: High | L55: removed catalog code and file extension | M55: SF339-09 - Elyar Fox - A Billion Girls.cdg
A56: =CONCATENATE(B56,C56) -> Headlights (Clean)Eminem feat. Nate Ruess | B56: Headlights (Clean) | C56: Eminem feat. Nate Ruess | D56: 2013 | E56: 2010s | F56: Hip-Hop, Rap | H56: Male | J56: High | L56: kept clean version tag | M56: MRH118-05 - Eminem FT. Nate Ruess - Headlights (Clean).cdg
A57: =CONCATENATE(B57,C57) -> Cold OneEric Church | B57: Cold One | C57: Eric Church | D57: 2014 | E57: 2010s | F57: Country | H57: Male | J57: High | L57: removed catalog code and file extension | M57: KCD1408-01 - Eric Church - Cold One.cdg
A58: =CONCATENATE(B58,C58) -> Over When It’s OverEric Church | B58: Over When It’s Over | C58: Eric Church | D58: 2012 | E58: 2010s | F58: Country | H58: Male | J58: High | M58: ASK1209C-05 - Eric Church - Over When It's Over.zip
A59: =CONCATENATE(B59,C59) -> One More Day (Stay with Me)Example | B59: One More Day (Stay with Me) | C59: Example | D59: 2014 | E59: 2010s | F59: Dance / Disco, Pop | H59: Male | J59: High | L59: normalized title capitalization | M59: MRH119-07 - Example - One More Day (Stay With Me).cdg
A60: =CONCATENATE(B60,C60) -> BO$$Fifth Harmony | B60: BO$$ | C60: Fifth Harmony | D60: 2014 | E60: 2010s | F60: Pop, R&B | G60: Group Songs | H60: Female | J60: High | L60: preserved stylized title | M60: G28954 - BO$$ - Fifth Harmony.cdg
A61: =CONCATENATE(B61,C61) -> The WalkerFitz and the Tantrums | B61: The Walker | C61: Fitz and the Tantrums | D61: 2013 | E61: 2010s | F61: Pop, Alternative / Indie | G61: Group Songs | H61: Male | J61: High | M61: ASK1408-01 - Fitz & The Tantrums - The Walker.cdg
A62: =CONCATENATE(B62,C62) -> The Walker (with vocal)Fitz and the Tantrums | B62: The Walker (with vocal) | C62: Fitz and the Tantrums | D62: 2013 | E62: 2010s | F62: Pop, Alternative / Indie | G62: Group Songs | H62: Male | J62: High | L62: kept alt vocal version | M62: ASK1408-09 - Fitz & The Tantrums - The Walker Wvocal.cdg
A63: =CONCATENATE(B63,C63) -> DirtFlorida Georgia Line | B63: Dirt | C63: Florida Georgia Line | D63: 2014 | E63: 2010s | F63: Country | H63: Male | J63: High | M63: ASK1408-04 - Florida Georgia Line - Dirt.cdg
A64: =CONCATENATE(B64,C64) -> Dirt (with vocal)Florida Georgia Line | B64: Dirt (with vocal) | C64: Florida Georgia Line | D64: 2014 | E64: 2010s | F64: Country | H64: Male | J64: High | L64: kept alt vocal version | M64: ASK1408-12 - Florida Georgia Line - Dirt Wvocal.cdg
A65: =CONCATENATE(B65,C65) -> BlameCalvin Harris feat. John Newman | B65: Blame | C65: Calvin Harris feat. John Newman | D65: 2014 | E65: 2010s | F65: Dance / Disco, Pop | H65: Male | J65: High | L65: normalized featured artist formatting
A66: =CONCATENATE(B66,C66) -> Blame It on MeGeorge Ezra | B66: Blame It on Me | C66: George Ezra | D66: 2014 | E66: 2010s | F66: Pop | H66: Male | J66: High | L66: normalized title capitalization | M66: SF345-10 - George Ezra - Blame It On Me.cdg
A67: =CONCATENATE(B67,C67) -> BudapestGeorge Ezra | B67: Budapest | C67: George Ezra | D67: 2013 | E67: 2010s | F67: Pop | G67: Group Songs | H67: Male | J67: High | L67: removed catalog code and file extension
A68: =CONCATENATE(B68,C68) -> Love Is EverythingGeorge Strait | B68: Love Is Everything | C68: George Strait | D68: 2013 | E68: 2010s | F68: Country | H68: Male | J68: High | L68: removed catalog code and file extension | M68: KCD1408-04 - George Strait - Love Is Everything.cdg
A69: =CONCATENATE(B69,C69) -> Burnin' UpJessie J feat. 2 Chainz | B69: Burnin' Up | C69: Jessie J feat. 2 Chainz | D69: 2014 | E69: 2010s | F69: Pop | G69: Group Songs | H69: Female | J69: High | L69: normalized featured artist formatting | M69: SF345-08 - Jessie J Ft. 2 Chainz - Burnin' Up.cdg
A70: =CONCATENATE(B70,C70) -> Adore YouHarry Styles | B70: Adore You | C70: Harry Styles | D70: 2019 | E70: 2010s | F70: Pop | H70: Male | J70: High | M70: Harry_Styles_Adore_You(MP3+CDG_Karaoke)_10366793.zip
A71: =CONCATENATE(B71,C71) -> As It WasHarry Styles | B71: As It Was | C71: Harry Styles | D71: 2022 | E71: 2020s | F71: Pop | H71: Male | J71: High | M71: Harry_Styles_As_It_Was(MP3+CDG_Karaoke)_10602886.zip
A72: =CONCATENATE(B72,C72) -> Keep DrivingHarry Styles | B72: Keep Driving | C72: Harry Styles | D72: 2022 | E72: 2020s | F72: Pop | H72: Male | J72: High | M72: Harry_Styles_Keep_Driving(MP3+CDG_Karaoke)_10631199.zip
A73: =CONCATENATE(B73,C73) -> MatildaHarry Styles | B73: Matilda | C73: Harry Styles | D73: 2022 | E73: 2020s | F73: Pop | H73: Male | J73: High | M73: Harry_Styles_Matilda(MP3+CDG_Karaoke)_10619342.zip
A74: =CONCATENATE(B74,C74) -> Sign of the TimesHarry Styles | B74: Sign of the Times | C74: Harry Styles | D74: 2017 | E74: 2010s | F74: Pop, Rock | H74: Male | J74: High | M74: Harry_Styles_Sign_of_the_Times(MP3+CDG_Karaoke)_10184008.zip
A75: =CONCATENATE(B75,C75) -> Sweet CreatureHarry Styles | B75: Sweet Creature | C75: Harry Styles | D75: 2017 | E75: 2010s | F75: Pop | H75: Male | J75: High | M75: Harry_Styles_Sweet_Creature(MP3+CDG_Karaoke)_10428735.zip
A76: =CONCATENATE(B76,C76) -> Equip SunglassesHot Mulligan | B76: Equip Sunglasses | C76: Hot Mulligan | D76: 2020 | E76: 2020s | F76: Alternative / Indie, Emo / Pop Punk | H76: Male | J76: High | M76: Hot_Mulligan_Equip_Sunglasses(MP3+CDG_Karaoke)_10920728.zip
A77: =CONCATENATE(B77,C77) -> FancyIggy Azalea feat. Charli XCX | B77: Fancy | C77: Iggy Azalea feat. Charli XCX | D77: 2014 | E77: 2010s | F77: Hip-Hop, Rap, Pop | G77: Group Songs | H77: Female | J77: High | L77: normalized featured artist formatting | M77: SF339-05 - Iggy Azalea Feat. Charli XCX - Fancy.cdg
A78: =CONCATENATE(B78,C78) -> ChandelierSia | B78: Chandelier | C78: Sia | D78: 2014 | E78: 2010s | F78: Pop | G78: Group Songs | H78: Female | J78: High | L78: removed catalog code and file extension
A79: =CONCATENATE(B79,C79) -> Mad WorldJasmine Thompson | B79: Mad World | C79: Jasmine Thompson | D79: 2014 | E79: 2010s | F79: Pop | H79: Female | J79: Medium | K79: Yes | L79: cover version (Tears for Fears original) | M79: Jasmine_Thompson_Mad_World(MP3+CDG_Karaoke)_10188076.zip
A80: =CONCATENATE(B80,C80) -> Burnin' It DownJason Aldean | B80: Burnin' It Down | C80: Jason Aldean | D80: 2014 | E80: 2010s | F80: Country | H80: Male | J80: High | L80: removed catalog code and file extension | M80: G28968 - Burnin' It Down - Jason Aldean.cdg
A81: =CONCATENATE(B81,C81) -> Burnin’ It DownJason Aldean | B81: Burnin’ It Down | C81: Jason Aldean | D81: 2014 | E81: 2010s | F81: Country | H81: Male | J81: High | M81: ASK1408-05 - Jason Aldean - Burnin' It Down.cdg
A82: =CONCATENATE(B82,C82) -> Burnin’ It Down (with vocal)Jason Aldean | B82: Burnin’ It Down (with vocal) | C82: Jason Aldean | D82: 2014 | E82: 2010s | F82: Country | H82: Male | J82: High | L82: kept alt vocal version | M82: ASK1408-13 - Jason Aldean - Burnin' It Down Wvocal.cdg
A83: =CONCATENATE(B83,C83) -> It's So Hard to Say Goodbye to YesterdayJason Mraz | B83: It's So Hard to Say Goodbye to Yesterday | C83: Jason Mraz | D83: 2014 | E83: 2010s | F83: Pop | H83: Male | J83: Medium | K83: Yes | L83: likely cover; year reflects Jason Mraz recording, not original song | M83: KCD1407-2-09 - Jason Mraz - It's So Hard To Say Goodbye To Yesterday.cdg
A84: =CONCATENATE(B84,C84) -> Don't Tell 'Em (Explicit)Jeremih feat. YG | B84: Don't Tell 'Em (Explicit) | C84: Jeremih feat. YG | D84: 2014 | E84: 2010s | F84: R&B, Hip-Hop, Rap | H84: Male | J84: High | L84: removed catalog code and file extension | M84: G28948 - Don't Tell 'Em (explicit) - Jeremih feat. YG.cdg
A85: =CONCATENATE(B85,C85) -> ClassicMKTO | B85: Classic | C85: MKTO | D85: 2013 | E85: 2010s | F85: Pop | G85: Group Songs | H85: Male | J85: High | L85: removed catalog code and file extension
A86: =CONCATENATE(B86,C86) -> Midnight AngelJimmy Rankin | B86: Midnight Angel | C86: Jimmy Rankin | D86: 2001 | E86: 2000s | F86: Country | H86: Male | I86: Possible Duplicate | J86: Medium | K86: Yes | L86: variant version present | M86: DFK090-07 - Jimmy Rankin - Midnight Angel (Wbgv).zip
A87: =CONCATENATE(B87,C87) -> Midnight Angel (with vocal)Jimmy Rankin | B87: Midnight Angel (with vocal) | C87: Jimmy Rankin | D87: 2001 | E87: 2000s | F87: Country | H87: Male | J87: Medium | K87: Yes | L87: verify year | M87: DFK090-06 - Jimmy Rankin - Midnight Angel (Wvocal).zip
A88: =CONCATENATE(B88,C88) -> Anywhere for YouJohn Martin | B88: Anywhere for You | C88: John Martin | D88: 2014 | E88: 2010s | F88: Dance / Disco, Pop | H88: Male | J88: High | L88: normalized title capitalization | M88: SF339-12 - John Martin - Anywhere For You.cdg
A89: =CONCATENATE(B89,C89) -> The Love I’m Frightened OfKatie Melua | B89: The Love I’m Frightened Of | C89: Katie Melua | D89: 2013 | E89: 2010s | F89: Pop | H89: Female | I89: Possible Duplicate | J89: Medium | K89: Yes | L89: title normalization uncertain | M89: DFK090-10 - Katie Melua - Love I'm Frightened Of (Wbgv).zip
A90: =CONCATENATE(B90,C90) -> The Love I’m Frightened Of (with vocal)Katie Melua | B90: The Love I’m Frightened Of (with vocal) | C90: Katie Melua | D90: 2013 | E90: 2010s | F90: Pop | H90: Female | J90: Medium | K90: Yes | L90: title normalization uncertain | M90: DFK090-09 - Katie Melua - Love I'm Frightened Of, The (Wvocal).zip
A91: =CONCATENATE(B91,C91) -> StillKaty B | B91: Still | C91: Katy B | D91: 2014 | E91: 2010s | F91: Pop, R&B | H91: Female | J91: High | L91: removed catalog code and file extension | M91: SF340-15 - Katy B - Still.cdg
A92: =CONCATENATE(B92,C92) -> ComebackElla Eyre | B92: Comeback | C92: Ella Eyre | D92: 2014 | E92: 2010s | F92: Pop, R&B | H92: Female | J92: High | L92: removed catalog code and file extension | M92: SF344-18 - Ella Eyre - Comeback.cdg
A93: =CONCATENATE(B93,C93) -> It Takes TwoKaty Perry | B93: It Takes Two | C93: Katy Perry | D93: 2013 | E93: 2010s | F93: Pop | H93: Female | J93: Medium | K93: Yes | L93: verify track attribution | M93: DFK090-02 - Katy Perry - It Takes Two.zip
A94: =CONCATENATE(B94,C94) -> It Takes Two (with vocal)Katy Perry | B94: It Takes Two (with vocal) | C94: Katy Perry | D94: 2013 | E94: 2010s | F94: Pop | H94: Female | J94: Medium | K94: Yes | L94: lesser-known track, verify | M94: DFK090-01 - Katy Perry - It Takes Two (Wvocal).zip
A95: =CONCATENATE(B95,C95) -> Already GoneKelly Clarkson | B95: Already Gone | C95: Kelly Clarkson | D95: 2009 | E95: 2000s | F95: Pop | H95: Female | J95: High | M95: Kelly_Clarkson_Already_Gone(MP3+CDG_Karaoke)_47050.zip
A96: =CONCATENATE(B96,C96) -> Happier Than EverKelly Clarkson | B96: Happier Than Ever | C96: Kelly Clarkson | D96: 2021 | E96: 2020s | F96: Pop | H96: Female | J96: Medium | K96: Yes | L96: cover vs Billie Eilish original | M96: Kelly_Clarkson_Happier_Than_Ever(MP3+CDG_Karaoke)_10619919.zip
A97: =CONCATENATE(B97,C97) -> American KidsKenny Chesney | B97: American Kids | C97: Kenny Chesney | D97: 2014 | E97: 2010s | F97: Country | G97: Group Songs | H97: Male | J97: High | L97: removed catalog code and file extension | M97: G28898 - American Kids - Kenny Chesney.cdg
A98: =CONCATENATE(B98,C98) -> Crazy Stupid LoveCheryl Cole feat. Tinie Tempah | B98: Crazy Stupid Love | C98: Cheryl Cole feat. Tinie Tempah | D98: 2014 | E98: 2010s | F98: Pop, Dance / Disco | G98: Group Songs | H98: Female | J98: High | L98: normalized featured artist formatting
A99: =CONCATENATE(B99,C99) -> I Was Gonna CancelKylie Minogue | B99: I Was Gonna Cancel | C99: Kylie Minogue | D99: 2014 | E99: 2010s | F99: Pop, Dance / Disco | H99: Female | J99: High | L99: removed catalog code and file extension | M99: SF340-16 - Kylie Minogue - I Was Gonna Cancel.cdg
A100: =CONCATENATE(B100,C100) -> Let Me Down GentlyLa Roux | B100: Let Me Down Gently | C100: La Roux | D100: 2014 | E100: 2010s | F100: Pop | H100: Female | J100: High | L100: removed catalog code and file extension | M100: SF341-04 - La Roux - Let Me Down Gently.cdg
...

Sheet 2-4
A1: Name
A2: Alicia_Keys_Girl_On_Fire_(Main_Version)_160717.mp4
A3: Bad Romance.3gp
A4: LMFAO - Party Rock Anthem
A5: Adele - Rolling In The Deep
A6: SF296-09 - Adele - Make You Feel My Love
A7: SF302-18 - Adele - Promise This
A8: SF303-18 Adele - Set Fire To The Rain
A9: SF307-01 - Adele - One And Only
A10: SFPL023-08 - Adele - Chasing Pavements
A11: SFPL023-09 - Adele - Cold Shoulder
A12: Zoom Karaoke - Someone Like You - Adele
... A1377: Zac Brown Band - Homegrown

Sheet songs
A1: FullName | B1: Name
A2: D:\Karaoke\new\01-30-26\Blink_182_Mutt(MP3+CDG_Karaoke)_10964551.zip | B2: Blink_182_Mutt(MP3+CDG_Karaoke)_10964551.zip
A3: D:\Karaoke\new\01-30-26\Bowling_for_Soup_High_School_Never_Ends(MP3+CDG_Karaoke)_10558576.zip | B3: Bowling_for_Soup_High_School_Never_Ends(MP3+CDG_Karaoke)_10558576.zip
A4: D:\Karaoke\new\01-30-26\Chris_LeDoux_Stampede(MP3+CDG_Karaoke)_10405499.zip | B4: Chris_LeDoux_Stampede(MP3+CDG_Karaoke)_10405499.zip
A5: D:\Karaoke\new\01-30-26\Cody_Johnson_Travelin_Soldier(MP3+CDG_Karaoke)_10989200.zip | B5: Cody_Johnson_Travelin_Soldier(MP3+CDG_Karaoke)_10989200.zip
A6: D:\Karaoke\new\01-30-26\Harry_Styles_Adore_You(MP3+CDG_Karaoke)_10366793.zip | B6: Harry_Styles_Adore_You(MP3+CDG_Karaoke)_10366793.zip
A7: D:\Karaoke\new\01-30-26\Harry_Styles_As_It_Was(MP3+CDG_Karaoke)_10602886.zip | B7: Harry_Styles_As_It_Was(MP3+CDG_Karaoke)_10602886.zip
A8: D:\Karaoke\new\01-30-26\Harry_Styles_Keep_Driving(MP3+CDG_Karaoke)_10631199.zip | B8: Harry_Styles_Keep_Driving(MP3+CDG_Karaoke)_10631199.zip
A9: D:\Karaoke\new\01-30-26\Harry_Styles_Matilda(MP3+CDG_Karaoke)_10619342.zip | B9: Harry_Styles_Matilda(MP3+CDG_Karaoke)_10619342.zip
A10: D:\Karaoke\new\01-30-26\Harry_Styles_Sign_of_the_Times(MP3+CDG_Karaoke)_10184008.zip | B10: Harry_Styles_Sign_of_the_Times(MP3+CDG_Karaoke)_10184008.zip
A11: D:\Karaoke\new\01-30-26\Harry_Styles_Sweet_Creature(MP3+CDG_Karaoke)_10428735.zip | B11: Harry_Styles_Sweet_Creature(MP3+CDG_Karaoke)_10428735.zip
A12: D:\Karaoke\new\01-30-26\Hot_Mulligan_Equip_Sunglasses(MP3+CDG_Karaoke)_10920728.zip | B12: Hot_Mulligan_Equip_Sunglasses(MP3+CDG_Karaoke)_10920728.zip
... A2387: D:\Karaoke\new\Kkaraoke 2-23-25\Zach_Bryan_Sun_to_Me(MP3+CDG_Karaoke)_10727727.zip | B2387: Zach_Bryan_Sun_to_Me(MP3+CDG_Karaoke)_10727727.zip

Sheet songs2
A1: FullName | B1: Name
A2: D:\Karaoke\butches laptop\Karaoke\Alicia_Keys_Girl_On_Fire_(Main_Version)_160717.mp4 | B2: Alicia_Keys_Girl_On_Fire_(Main_Version)_160717.mp4
A3: D:\Karaoke\butches laptop\Karaoke\Bad Romance.3gp | B3: Bad Romance.3gp
A4: D:\Karaoke\butches laptop\Karaoke\ - LMFAO - Party Rock Anthem\- LMFAO - Party Rock Anthem.cdg | B4: =- LMFAO - Party Rock Anthem.cdg -> #NAME?
A5: D:\Karaoke\butches laptop\Karaoke\ - LMFAO - Party Rock Anthem\- LMFAO - Party Rock Anthem.mp3 | B5: =- LMFAO - Party Rock Anthem.mp3 -> #NAME?
A6: D:\Karaoke\butches laptop\Karaoke\Adele\Adele - Rolling In The Deep [Karaoke].cdg | B6: Adele - Rolling In The Deep [Karaoke].cdg
A7: D:\Karaoke\butches laptop\Karaoke\Adele\Adele - Rolling In The Deep [Karaoke].mp3 | B7: Adele - Rolling In The Deep [Karaoke].mp3
A8: D:\Karaoke\butches laptop\Karaoke\Adele\SF296-09 - Adele - Make You Feel My Love.cdg | B8: SF296-09 - Adele - Make You Feel My Love.cdg
A9: D:\Karaoke\butches laptop\Karaoke\Adele\SF296-09 - Adele - Make You Feel My Love.mp3 | B9: SF296-09 - Adele - Make You Feel My Love.mp3
A10: D:\Karaoke\butches laptop\Karaoke\Adele\SF302-18 - Adele - Promise This.cdg | B10: SF302-18 - Adele - Promise This.cdg
A11: D:\Karaoke\butches laptop\Karaoke\Adele\SF302-18 - Adele - Promise This.mp3 | B11: SF302-18 - Adele - Promise This.mp3
A12: D:\Karaoke\butches laptop\Karaoke\Adele\SF303-18 Adele - Set Fire To The Rain.cdg | B12: SF303-18 Adele - Set Fire To The Rain.cdg
A13: D:\Karaoke\butches laptop\Karaoke\Adele\SF303-18 Adele - Set Fire To The Rain.mp3 | B13: SF303-18 Adele - Set Fire To The Rain.mp3
A14: D:\Karaoke\butches laptop\Karaoke\Adele\SF307-01 - Adele - One And Only.cdg | B14: SF307-01 - Adele - One And Only.cdg
A15: D:\Karaoke\butches laptop\Karaoke\Adele\SF307-01 - Adele - One And Only.mp3 | B15: SF307-01 - Adele - One And Only.mp3
A16: D:\Karaoke\butches laptop\Karaoke\Adele\SFPL023-08 - Adele - Chasing Pavements.cdg | B16: SFPL023-08 - Adele - Chasing Pavements.cdg
A17: D:\Karaoke\butches laptop\Karaoke\Adele\SFPL023-08 - Adele - Chasing Pavements.mp3 | B17: SFPL023-08 - Adele - Chasing Pavements.mp3
... A1475: D:\Karaoke\butches laptop\Karaoke\Zac Brown Band - Keep Me In Mind\Zac Brown Band - Keep Me In Mind.mp3 | B1475: Zac Brown Band - Keep Me In Mind.mp3

Sheet songs4
A1: Name
A2: Blake Shelton - Hillbilly Bone.cdg
A3: Blake Shelton - Hillbilly Bone.mp3
A4: AC-DC - Back In Black.cdg
A5: AC-DC - Back In Black.mp3
A6: AC-DC - Big Balls.cdg
A7: AC-DC - Big Balls.mp3
A8: AC-DC - For Those About To Rock.cdg
A9: AC-DC - For Those About To Rock.mp3
A10: AC-DC - Girls Got Rythm.cdg
A11: AC-DC - Girls Got Rythm.MP3
A12: AC-DC - Hells Bells.cdg
... A1127: SC3437-07 - Miranda Lambert - Bring Me Down.mp3

Sheet songs3
A1: Name
A2: - Eli Young Band - Drunk Last Night.zip
A3: A Thousand Horses - Smoke.zip
A4: Aldean, Jason - Dont You Wanna Stay (duet Kelly Clarkson).zip
A5: Aldean, Jason - Just Gettin Started.zip
A6: Aldean, Jason - Take A Little Ride.zip
A7: Allan, Gary - Every Storm (Runs Out Of Rain).zip
A8: Amazon-MP3-1428732197.amz
A9: Bates, Greg - Did It For The Girl.zip
A10: Bentley, Dierks - Say You Do.zip
A11: BKD - Little Big Town - Girl Crush.zip
A12: BKD - Musgraves, Kacey - Blowin Smoke.zip
... A44: Little Big Town - Day Drinking.zip
A45: Little Big Town - Your Side Of the Bed.zip | K45: 1475
A46: Love And Theft - Angel Eyes.zip | K46: 79
A47: Love And Theft - Whiskey On My Breath (1).zip | K47: 1127
A48: Love And Theft - Whiskey On My Breath.zip | K48: =SUM(K45:K47) -> 2681
A49: Lynch, Dustin - Cowboys And Angels.zip
A50: Magic! - Rude.zip
A51: Maroon 5 - Sugar (1).zip
A52: Maroon 5 - Sugar.zip
A53: Mars, Bruno - Uptown Funk (w. Mark Ronson).zip
A54: McEntire, Reba - Going Out Like That.zip
A55: Miguel - Adorn.zip
A56: Moore, Kip - Beer Money.zip
A57: Moore, Kip - Something Bout A Truck.zip
A58: Mumford and Sons - Little Lion Man.zip
A59: Musiq - Halfcrazy.zip
A60: Old Crow Medicine Show - Wagon Wheel.zip
... A79: Zac Brown Band - Homegrown.zip
